hephaestus/_internal/meta.py
hephaestus/common/constants.py
hephaestus/common/exceptions.py
hephaestus/common/types.py
hephaestus/decorators/reference.py
hephaestus/decorators/track.py
hephaestus/io/file.py
hephaestus/io/logging.py
hephaestus/io/stream.py
hephaestus/io/subprocess.py
hephaestus/patterns/singleton.py
hephaestus/testing/swte.py
hephaestus/testing/mock/threading.py
hephaestus/testing/pytest/configure.py
hephaestus/testing/pytest/fixtures/__init__.py
hephaestus/testing/pytest/fixtures/env.py
hephaestus/testing/pytest/fixtures/logging.py
hephaestus_lib-0.2.0.dist-info/LICENSE
hephaestus_lib-0.2.0.dist-info/METADATA
hephaestus_lib-0.2.0.dist-info/WHEEL
hephaestus_lib-0.2.0.dist-info/top_level.txt
hephaestus_lib-0.2.0.dist-info/RECORD
