Metadata-Version: 2.2
Name: hephaestus-lib
Version: 0.2.0
Summary: A collection of useful Python Classes, Methods, and Constants
Author-email: Malakai Spann <MalakaiSpann@gmail.com>
License: MIT License
Project-URL: Repository, https://github.com/KayDVC/hephaestus/
Classifier: Intended Audience :: Developers
Classifier: License :: OSI Approved :: MIT License
Classifier: Programming Language :: Python
Classifier: Programming Language :: Python :: 3
Classifier: Programming Language :: Python :: 3 :: Only
Classifier: Topic :: Software Development
Classifier: Topic :: Software Development :: Libraries :: Python Modules
Classifier: Operating System :: Microsoft :: Windows
Classifier: Operating System :: POSIX
Classifier: Operating System :: Unix
Classifier: Operating System :: MacOS
Requires-Python: >=3.10
License-File: LICENSE
